.gitignore
AUTHORS
LICENSE
README.md
setup.py
wlby
wallaby/FXUI.py
wallaby/__init__.py
wallaby/qt_combat.py
wallaby/apps/__init__.py
wallaby/apps/garbageCollector.py
wallaby/apps/wallabyApp.py
wallaby/apps/template/README
wallaby/apps/template/__init__.py
wallaby/apps/template/setup.py
wallaby/apps/template/deploy/app.iss
wallaby/apps/template/deploy/app.py
wallaby/apps/template/deploy/setup.py
wallaby/apps/template/deploy/wallaby.icns
wallaby/apps/template/deploy/wallaby.ico
wallaby/apps/template/images/wallaby.icns
wallaby/apps/template/wallaby/__init__.py
wallaby/apps/template/wallaby/apps/__init__.py
wallaby/apps/template/wallaby/apps/appname/__init__.py
wallaby/apps/template/wallaby/apps/appname/app.qrc
wallaby/apps/template/wallaby/apps/appname/mainWindow.py
wallaby/apps/template/wallaby/apps/appname/mainWindow.ui
wallaby/apps/template/wallaby/apps/appname/couchapp/.couchappignore
wallaby/apps/template/wallaby/apps/appname/couchapp/.couchapprc
wallaby/apps/template/wallaby/apps/appname/couchapp/_id
wallaby/apps/template/wallaby/apps/appname/couchapp/filters/all.js
wallaby/apps/template/wallaby/apps/appname/couchapp/views/all/map.js
wallaby/apps/template/wallaby/apps/appname/es/example.json
wallaby/apps/template/wallaby/apps/appname/images/__empty__
wallaby/apps/template/wallaby/apps/appname/isheet/__init__.py
wallaby/apps/template/wallaby/apps/appname/peer/__init__.py
wallaby/apps/template/wallaby/apps/appname/plugins/__init__.py
wallaby/apps/template/wallaby/apps/appname/prefs/__init__.py
wallaby/apps/template/wallaby/apps/appname/rooms/__init__.py
wallaby/apps/template/wallaby/apps/appname/scripts/__init__.py
wallaby/apps/template/wallaby/apps/appname/widgets/__init__.py
wallaby/frontends/__init__.py
wallaby/frontends/qt/UI_loginDialog.py
wallaby/frontends/qt/__init__.py
wallaby/frontends/qt/baseWindow.py
wallaby/frontends/qt/baseqobject.py
wallaby/frontends/qt/compile.py
wallaby/frontends/qt/loginDialog.py
wallaby/frontends/qt/loginDialog.ui
wallaby_frontend_qt.egg-info/PKG-INFO
wallaby_frontend_qt.egg-info/SOURCES.txt
wallaby_frontend_qt.egg-info/dependency_links.txt
wallaby_frontend_qt.egg-info/requires.txt
wallaby_frontend_qt.egg-info/top_level.txt